volttron/driver/interfaces/modbus/__init__.py
volttron/driver/interfaces/modbus/modbus.py
volttron_lib_modbus_driver-0.2.1rc0.dist-info/LICENSE
volttron_lib_modbus_driver-0.2.1rc0.dist-info/METADATA
volttron_lib_modbus_driver-0.2.1rc0.dist-info/WHEEL
volttron_lib_modbus_driver-0.2.1rc0.dist-info/RECORD
